acceso_polymarket/__init__.py
acceso_polymarket/client.py
acceso_polymarket/types.py
acceso_polymarket-1.0.0.dist-info/licenses/LICENSE
acceso_polymarket-1.0.0.dist-info/METADATA
acceso_polymarket-1.0.0.dist-info/WHEEL
acceso_polymarket-1.0.0.dist-info/top_level.txt
acceso_polymarket-1.0.0.dist-info/RECORD
