Metadata-Version: 2.4
Name: acceso-polymarket
Version: 1.0.0
Summary: Python SDK for Polymarket prediction markets via Acceso API
Author-email: Acceso <dev@acceso.dev>
License: MIT
Project-URL: Homepage, https://acceso.dev
Project-URL: Repository, https://github.com/acceso-dev/acceso-polymarket-python
Keywords: polymarket,prediction-markets,trading,crypto,web3,api,sdk
Classifier: Development Status :: 4 - Beta
Classifier: Intended Audience :: Developers
Classifier: Programming Language :: Python :: 3
Classifier: Programming Language :: Python :: 3.8
Classifier: Programming Language :: Python :: 3.9
Classifier: Programming Language :: Python :: 3.10
Classifier: Programming Language :: Python :: 3.11
Classifier: Programming Language :: Python :: 3.12
Requires-Python: >=3.8
License-File: LICENSE
Requires-Dist: requests>=2.28.0
Dynamic: license-file
